smithy_core/__init__.py
smithy_core/codecs.py
smithy_core/deserializers.py
smithy_core/documents.py
smithy_core/endpoints.py
smithy_core/exceptions.py
smithy_core/identity.py
smithy_core/interceptors.py
smithy_core/prelude.py
smithy_core/py.typed
smithy_core/retries.py
smithy_core/rfc3986.py
smithy_core/schemas.py
smithy_core/serializers.py
smithy_core/shapes.py
smithy_core/traits.py
smithy_core/types.py
smithy_core/utils.py
smithy_core/aio/__init__.py
smithy_core/aio/endpoints.py
smithy_core/aio/eventstream.py
smithy_core/aio/types.py
smithy_core/aio/utils.py
smithy_core/aio/interfaces/__init__.py
smithy_core/aio/interfaces/eventstream.py
smithy_core/aio/interfaces/identity.py
smithy_core/interfaces/__init__.py
smithy_core/interfaces/exceptions.py
smithy_core/interfaces/identity.py
smithy_core/interfaces/retries.py
smithy_core-0.0.1.dist-info/METADATA
smithy_core-0.0.1.dist-info/WHEEL
smithy_core-0.0.1.dist-info/licenses/NOTICE
smithy_core-0.0.1.dist-info/RECORD
